setup.py
sqlstring/__init__.py
sqlstring/sql_builder.py
sqlstring.egg-info/PKG-INFO
sqlstring.egg-info/SOURCES.txt
sqlstring.egg-info/dependency_links.txt
sqlstring.egg-info/requires.txt
sqlstring.egg-info/top_level.txt
tests/__init__.py
tests/test_deleteBuilder.py
tests/test_insertBuilder.py
tests/test_selectBuilder.py
tests/test_updateBuilder.py