Metadata-Version: 1.1
Name: sqlstring
Version: 0.1.2
Summary: sqlstring creates SQL query strings.
Home-page: https://github.com/saun4app/sqlstring
Author: Saun Shewanown
Author-email: saun4app@gmail.com
License: MIT
Keywords: sql string builder dataset sqlalchemy MySql PostgreSQL Sqlite
Platform: UNKNOWN
Classifier: Development Status :: 4 - Beta
Classifier: Intended Audience :: Developers
Classifier: License :: OSI Approved :: MIT License
Classifier: Operating System :: OS Independent
Classifier: Topic :: Database
Classifier: Programming Language :: Python :: 2.7
Classifier: Programming Language :: Python :: 3.4
